<annotation>
	<folder></folder>
	<filename>109_jpeg.rf.89daa289f669e016c98b60d835fa5267.jpg</filename>
	<path>109_jpeg.rf.89daa289f669e016c98b60d835fa5267.jpg</path>
	<source>
		<database>roboflow.ai</database>
	</source>
	<size>
		<width>1098</width>
		<height>1600</height>
		<depth>3</depth>
	</size>
	<segmented>0</segmented>
	<object>
		<name>InvoiceNumber</name>
		<pose>Unspecified</pose>
		<truncated>0</truncated>
		<difficult>0</difficult>
		<occluded>0</occluded>
		<bndbox>
			<xmin>205</xmin>
			<xmax>259</xmax>
			<ymin>419</ymin>
			<ymax>441</ymax>
		</bndbox>
	</object>
	<object>
		<name>InvoiceDate</name>
		<pose>Unspecified</pose>
		<truncated>0</truncated>
		<difficult>0</difficult>
		<occluded>0</occluded>
		<bndbox>
			<xmin>909</xmin>
			<xmax>1017</xmax>
			<ymin>422</ymin>
			<ymax>444</ymax>
		</bndbox>
	</object>
	<object>
		<name>TotalAmount</name>
		<pose>Unspecified</pose>
		<truncated>0</truncated>
		<difficult>0</difficult>
		<occluded>0</occluded>
		<bndbox>
			<xmin>1010</xmin>
			<xmax>1088</xmax>
			<ymin>1191</ymin>
			<ymax>1219</ymax>
		</bndbox>
	</object>
</annotation>
