<annotation>
	<folder></folder>
	<filename>94_jpeg.rf.a3078876309eec49908f5204b0ef7332.jpg</filename>
	<path>94_jpeg.rf.a3078876309eec49908f5204b0ef7332.jpg</path>
	<source>
		<database>roboflow.ai</database>
	</source>
	<size>
		<width>2550</width>
		<height>3300</height>
		<depth>3</depth>
	</size>
	<segmented>0</segmented>
	<object>
		<name>InvoiceNumber</name>
		<pose>Unspecified</pose>
		<truncated>0</truncated>
		<difficult>0</difficult>
		<occluded>0</occluded>
		<bndbox>
			<xmin>1924</xmin>
			<xmax>2106</xmax>
			<ymin>792</ymin>
			<ymax>858</ymax>
		</bndbox>
	</object>
	<object>
		<name>InvoiceDate</name>
		<pose>Unspecified</pose>
		<truncated>0</truncated>
		<difficult>0</difficult>
		<occluded>0</occluded>
		<bndbox>
			<xmin>2160</xmin>
			<xmax>2357</xmax>
			<ymin>789</ymin>
			<ymax>869</ymax>
		</bndbox>
	</object>
	<object>
		<name>TotalAmount</name>
		<pose>Unspecified</pose>
		<truncated>0</truncated>
		<difficult>0</difficult>
		<occluded>0</occluded>
		<bndbox>
			<xmin>2260</xmin>
			<xmax>2404</xmax>
			<ymin>2350</ymin>
			<ymax>2422</ymax>
		</bndbox>
	</object>
</annotation>
